sophgoface/__init__.py
sophgoface/main.so
sophgoface/app/__init__.py
sophgoface/app/common.so
sophgoface/app/face_analysis.so
sophgoface/model_zoo/__init__.py
sophgoface/model_zoo/arcface.so
sophgoface/model_zoo/model_zoo.so
sophgoface/model_zoo/retinaface.so
sophgoface/utils/__init__.py
sophgoface/utils/face_align.so
sophgoface-1.0.2.dist-info/METADATA
sophgoface-1.0.2.dist-info/WHEEL
sophgoface-1.0.2.dist-info/top_level.txt
sophgoface-1.0.2.dist-info/RECORD
