Metadata-Version: 2.1
Name: sophgoface
Version: 1.0.2
Summary: sophgoface
Home-page: UNKNOWN
Author: UNKNOWN
Author-email: UNKNOWN
License: Apache License 2.0
Platform: UNKNOWN
Requires-Dist: pyyaml
Requires-Dist: scikit-image
Requires-Dist: scikit-learn
